sply/__init__.py
sply/chat.py
sply/sp.py
sply/overmind/__init__.py
sply/overmind/node.py
sply-1.0.20.data/scripts/sply_chat_interact.py
sply-1.0.20.data/scripts/sply_double_chat.py
sply-1.0.20.dist-info/licenses/LICENSE.txt
sply-1.0.20.dist-info/METADATA
sply-1.0.20.dist-info/WHEEL
sply-1.0.20.dist-info/top_level.txt
sply-1.0.20.dist-info/RECORD
