Metadata-Version: 2.4
Name: sply
Version: 1.0.20
Summary: a bridge between real and simulated python interpreters
Home-page: https://github.com/richardbenson91477/sply
Author: Richard Benson
Author-email: richardbenson91477@protonmail.com
Maintainer: Richard Benson
Maintainer-email: richardbenson91477@protonmail.com
Requires-Python: >=3.8
License-File: LICENSE.txt
Dynamic: author
Dynamic: author-email
Dynamic: home-page
Dynamic: license-file
Dynamic: maintainer
Dynamic: maintainer-email
Dynamic: requires-python
Dynamic: summary
